paperlib_mcp/__init__.py
paperlib_mcp/chunking.py
paperlib_mcp/config.py
paperlib_mcp/db.py
paperlib_mcp/embeddings.py
paperlib_mcp/models_graph.py
paperlib_mcp/pdf_extract.py
paperlib_mcp/server.py
paperlib_mcp/settings.py
paperlib_mcp/storage.py
paperlib_mcp/tools/__init__.py
paperlib_mcp/tools/fetch.py
paperlib_mcp/tools/graph_canonicalize.py
paperlib_mcp/tools/graph_claim_grouping.py
paperlib_mcp/tools/graph_community.py
paperlib_mcp/tools/graph_extract.py
paperlib_mcp/tools/graph_maintenance.py
paperlib_mcp/tools/graph_relation_canonicalize.py
paperlib_mcp/tools/graph_summarize.py
paperlib_mcp/tools/graph_v12.py
paperlib_mcp/tools/health.py
paperlib_mcp/tools/import_pdf.py
paperlib_mcp/tools/review.py
paperlib_mcp/tools/search.py
paperlib_mcp/tools/writing.py
paperlib_mcp-0.1.5.dist-info/METADATA
paperlib_mcp-0.1.5.dist-info/WHEEL
paperlib_mcp-0.1.5.dist-info/entry_points.txt
paperlib_mcp-0.1.5.dist-info/RECORD
