Metadata-Version: 2.4
Name: paperlib-mcp
Version: 0.1.5
Summary: Paper Library MCP - 文献管理与检索 MCP 服务器
Requires-Python: >=3.11
Requires-Dist: boto3>=1.34.0
Requires-Dist: fastmcp>=2.0.0
Requires-Dist: httpx>=0.27.0
Requires-Dist: igraph>=0.11.0
Requires-Dist: leidenalg>=0.10.0
Requires-Dist: psycopg[binary]>=3.1.0
Requires-Dist: pydantic-settings>=2.0.0
Requires-Dist: pydantic>=2.0.0
Requires-Dist: pymupdf4llm>=0.0.17
